edacontainerwrapper/__init__.py
edacontainerwrapper/arguments.py
edacontainerwrapper/main.py
edacontainerwrapper/run.py
edacontainerwrapper/tools.py
edacontainerwrapper/version.py
eda_container_wrapper-0.0.4.dist-info/METADATA
eda_container_wrapper-0.0.4.dist-info/WHEEL
eda_container_wrapper-0.0.4.dist-info/entry_points.txt
eda_container_wrapper-0.0.4.dist-info/top_level.txt
eda_container_wrapper-0.0.4.dist-info/RECORD
