Metadata-Version: 2.1
Name: eda-container-wrapper
Version: 0.0.4
Summary: Generic wrapper tool around open source EDA tools that runs Docker containers
Home-page: https://github.com/librecores/eda-container-wrapper
Author: Stefan Wallentowitz
Author-email: stefan@wallentowitz.de
License: UNKNOWN
Platform: UNKNOWN
Classifier: License :: OSI Approved :: GNU Lesser General Public License v3 or later (LGPLv3+)
Classifier: Topic :: Utilities
